celeste/__init__.py
celeste/artifacts.py
celeste/auth.py
celeste/client.py
celeste/constraints.py
celeste/core.py
celeste/credentials.py
celeste/exceptions.py
celeste/http.py
celeste/io.py
celeste/mime_types.py
celeste/models.py
celeste/parameters.py
celeste/py.typed
celeste/streaming.py
celeste/structured_outputs.py
celeste/types.py
celeste/websocket.py
celeste/modalities/__init__.py
celeste/modalities/audio/__init__.py
celeste/modalities/audio/client.py
celeste/modalities/audio/constraints.py
celeste/modalities/audio/io.py
celeste/modalities/audio/languages.py
celeste/modalities/audio/models.py
celeste/modalities/audio/parameters.py
celeste/modalities/audio/streaming.py
celeste/modalities/audio/voices.py
celeste/modalities/audio/providers/__init__.py
celeste/modalities/audio/providers/elevenlabs/__init__.py
celeste/modalities/audio/providers/elevenlabs/client.py
celeste/modalities/audio/providers/elevenlabs/models.py
celeste/modalities/audio/providers/elevenlabs/parameters.py
celeste/modalities/audio/providers/elevenlabs/voices.py
celeste/modalities/audio/providers/google/__init__.py
celeste/modalities/audio/providers/google/client.py
celeste/modalities/audio/providers/google/models.py
celeste/modalities/audio/providers/google/parameters.py
celeste/modalities/audio/providers/google/voices.py
celeste/modalities/audio/providers/gradium/__init__.py
celeste/modalities/audio/providers/gradium/client.py
celeste/modalities/audio/providers/gradium/models.py
celeste/modalities/audio/providers/gradium/parameters.py
celeste/modalities/audio/providers/gradium/voices.py
celeste/modalities/audio/providers/openai/__init__.py
celeste/modalities/audio/providers/openai/client.py
celeste/modalities/audio/providers/openai/models.py
celeste/modalities/audio/providers/openai/parameters.py
celeste/modalities/audio/providers/openai/voices.py
celeste/modalities/embeddings/__init__.py
celeste/modalities/embeddings/client.py
celeste/modalities/embeddings/io.py
celeste_ai-0.9.6.dist-info/METADATA
celeste_ai-0.9.6.dist-info/WHEEL
celeste_ai-0.9.6.dist-info/licenses/LICENSE
celeste_ai-0.9.6.dist-info/RECORD
