Metadata-Version: 2.4
Name: celeste-ai
Version: 0.9.6
Summary: Open source, type-safe primitives for multi-modal AI. All capabilities, all providers, one interface
Project-URL: Homepage, https://withceleste.ai
Project-URL: Documentation, https://withceleste.ai/docs
Project-URL: Repository, https://github.com/withceleste/celeste-python
Project-URL: Issues, https://github.com/withceleste/celeste-python/issues
Author-email: Kamilbenkirane <kamil@withceleste.ai>
License: MIT
License-File: LICENSE
Keywords: ai,anthropic,claude,gemini,image-generation,multimodal,openai,sdk,speech-generation,text-embeddings,text-generation,video-generation
Classifier: Development Status :: 4 - Beta
Classifier: Intended Audience :: Developers
Classifier: License :: OSI Approved :: MIT License
Classifier: Operating System :: OS Independent
Classifier: Programming Language :: Python :: 3
Classifier: Programming Language :: Python :: 3.12
Classifier: Programming Language :: Python :: 3.13
Classifier: Topic :: Scientific/Engineering :: Artificial Intelligence
Classifier: Typing :: Typed
Requires-Python: >=3.12
Requires-Dist: asgiref>=3.11.0
Requires-Dist: filetype>=1.2.0
Requires-Dist: google-auth>=2.0.0
Requires-Dist: httpx-sse>=0.4.0
Requires-Dist: httpx>=0.27.0
Requires-Dist: pydantic-settings>=2.0
Requires-Dist: pydantic>=2.0
Requires-Dist: python-dotenv>=1.0.0
Requires-Dist: websockets>=15.0
